tb/sdram_memory_model.v
`timescale 1ns / 1ps
//////////////////////////////////////////////////////////////////////////////////
// Company: 
// Engineer: 
// 
// Create Date: 07.09.2026 11:51:56
// Design Name: 
// Module Name: sdram_memory_model
// Project Name: 
// Target Devices: 
// Tool Versions: 
// Description: 
// 
// Dependencies: 
// 
// Revision:
// Revision 0.01 - File Created
// Additional Comments:
// 
//////////////////////////////////////////////////////////////////////////////////


module sdram_memory_model(


input clk,


input write_enable,


input read_enable,


input [23:0] address,


inout [15:0] data_bus


);


// Memory Array

reg [15:0] memory [0:1023];


// Data output register

reg [15:0] data_out;


// Tri-state control

assign data_bus = read_enable ? data_out : 16'bz;



// Write Operation

always @(posedge clk)

begin


if(write_enable)

begin

memory[address[9:0]] <= data_bus;

end



end



// Read Operation

always @(posedge clk)

begin


if(read_enable)

begin

data_out <= memory[address[9:0]];

end


end



endmodule

tb/sdram_scoreboard.v
`timescale 1ns/1ps

//====================================================
// File Name : sdram_scoreboard.v
// Project   : High Speed SDRAM Memory Controller
// Purpose   : Read/Write Checker
//====================================================

module sdram_scoreboard
(

input write_check,

input read_check,

input [23:0] address,

input [15:0] write_data,

input [15:0] read_data

);


//====================================================
// Reference Memory
//====================================================

reg [15:0] expected_memory [0:1023];


integer i;


//====================================================
// Initialize Memory
//====================================================

initial
begin

for(i=0;i<1024;i=i+1)

begin

expected_memory[i] = 16'h0000;

end

end



//====================================================
// Write Checking
//====================================================

always @(posedge write_check)
begin

expected_memory[address[9:0]] = write_data;


$display("--------------------------------");

$display("SCOREBOARD WRITE");

$display("ADDRESS = %h DATA = %h",
address,
write_data);

$display("--------------------------------");


end



//====================================================
// Read Checking
//====================================================

always @(posedge read_check)
begin


if(expected_memory[address[9:0]] == read_data)

begin


$display("--------------------------------");

$display("PASS");

$display("ADDRESS = %h EXPECTED = %h RECEIVED = %h",
address,
expected_memory[address[9:0]],
read_data);

$display("--------------------------------");


end


else

begin


$display("--------------------------------");

$display("FAIL");

$display("ADDRESS = %h EXPECTED = %h RECEIVED = %h",
address,
expected_memory[address[9:0]],
read_data);

$display("--------------------------------");


end


end


endmodule

rtl/sdram_address_mapping.v
`timescale 1ns / 1ps
//////////////////////////////////////////////////////////////////////////////////
// Company: 
// Engineer: 
// 
// Create Date: 07.09.2026 11:32:47
// Design Name: 
// Module Name: sdram_address_mapping
// Project Name: 
// Target Devices: 
// Tool Versions: 
// Description: 
// 
// Dependencies: 
// 
// Revision:
// Revision 0.01 - File Created
// Additional Comments:
// 
//////////////////////////////////////////////////////////////////////////////////


//====================================================
// File Name : sdram_address_mapping.v
// Project   : High Speed SDRAM Memory Controller
// Purpose   : Address Mapping for SDRAM
//====================================================


module sdram_address_mapping(

input [23:0] address,


output [12:0] row_address,


output [9:0] column_address,


output [1:0] bank_address

);



// Row Address

assign row_address = address[21:10];



// Column Address

assign column_address = address[9:0];



// Bank Address

assign bank_address = address[23:22];



endmodule

rtl/sdram_controller_fsm.v
`timescale 1ns / 1ps
//////////////////////////////////////////////////////////////////////////////////
// Company: 
// Engineer: 
// 
// Create Date: 07.09.2026 11:31:55
// Design Name: 
// Module Name: sdram_controller_fsm
// Project Name: 
// Target Devices: 
// Tool Versions: 
// Description: 
// 
// Dependencies: 
// 
// Revision:
// Revision 0.01 - File Created
// Additional Comments:
// 
//////////////////////////////////////////////////////////////////////////////////


//====================================================
// File Name : sdram_controller_fsm.v
// Project   : High Speed SDRAM Memory Controller
// Purpose   : SDRAM Controller State Machine
//====================================================


module sdram_controller_fsm(

input clk,

input reset,


output reg [3:0] state

);


//====================================================
// State Declaration
//====================================================

parameter IDLE      = 4'd0;

parameter INIT      = 4'd1;

parameter ACTIVATE  = 4'd2;

parameter READ      = 4'd3;

parameter WRITE     = 4'd4;

parameter PRECHARGE = 4'd5;

parameter REFRESH   = 4'd6;

parameter WAIT      = 4'd7;



//====================================================
// FSM Sequential Logic
//====================================================

always @(posedge clk)

begin


if(reset)

begin

state <= INIT;

end


else

begin


case(state)



INIT:

begin

state <= IDLE;

end



IDLE:

begin

state <= ACTIVATE;

end



ACTIVATE:

begin

state <= WAIT;

end



WAIT:

begin

state <= READ;

end



READ:

begin

state <= PRECHARGE;

end



WRITE:

begin

state <= PRECHARGE;

end



PRECHARGE:

begin

state <= REFRESH;

end



REFRESH:

begin

state <= IDLE;

end



default:

begin

state <= IDLE;

end



endcase


end


end


endmodule

rtl/sdram_controller_top.v
`timescale 1ns / 1ps
//////////////////////////////////////////////////////////////////////////////////
// Company: 
// Engineer: 
// 
// Create Date: 07.09.2026 11:41:02
// Design Name: 
// Module Name: sdram_controller_top
// Project Name: 
// Target Devices: 
// Tool Versions: 
// Description: 
// 
// Dependencies: 
// 
// Revision:
// Revision 0.01 - File Created
// Additional Comments:
// 
//////////////////////////////////////////////////////////////////////////////////


//====================================================
// File Name : sdram_controller_top.v
// Project   : High Speed SDRAM Memory Controller
// Purpose   : Top Level SDRAM Controller Module
//====================================================


module sdram_controller_top(

input clk,

input reset,


// User Interface

input req,

input rw,

input [23:0] addr,

input [15:0] data_in,


output reg [15:0] data_out,


output busy,



// SDRAM Interface

output [12:0] sdram_addr,

output [1:0] sdram_bank,


inout [15:0] sdram_data,


output sdram_cs,

output sdram_ras,

output sdram_cas,

output sdram_we


);



// FSM State

wire [3:0] state;



//====================================================
// FSM Module
//====================================================

sdram_controller_fsm FSM
(

.clk(clk),

.reset(reset),

.state(state)

);



//====================================================
// Address Mapping
//====================================================

wire [12:0] row_address;

wire [9:0] column_address;



sdram_address_mapping ADDR_MAP
(

.address(addr),

.row_address(row_address),

.column_address(column_address),

.bank_address(sdram_bank)

);



assign sdram_addr = row_address;



//====================================================
// Busy Signal
//====================================================

assign busy = (state != 4'd0);



//====================================================
// SDRAM Control Signals
//====================================================

assign sdram_cs  = 1'b0;

assign sdram_ras = 1'b1;

assign sdram_cas = 1'b1;

assign sdram_we  = 1'b1;



// SDRAM Data Bus

// SDRAM data bus control

wire [15:0] write_data_bus;

assign sdram_data = (req && rw) ? data_in : 16'bz;



//====================================================
// Data Output
//====================================================

always @(posedge clk)

begin


if(reset)

data_out <= 16'b0;


else

data_out <= data_in;


end



endmodule

tb/tb_sdram_controller.v
`timescale 1ns/1ps

//====================================================
// Testbench : tb_sdram_controller
// Project   : High Speed SDRAM Memory Controller
//====================================================

module tb_sdram_controller;


//====================================================
// Clock and Reset
//====================================================

reg clk;
reg reset;


//====================================================
// User Interface
//====================================================

reg req;
reg rw;

reg [23:0] addr;

reg [15:0] data_in;


wire [15:0] data_out;

wire busy;


//====================================================
// SDRAM Interface
//====================================================

wire [12:0] sdram_addr;

wire [1:0] sdram_bank;

wire [15:0] sdram_data;

wire sdram_cs;

wire sdram_ras;

wire sdram_cas;

wire sdram_we;



//====================================================
// DUT Instance
//====================================================

sdram_controller_top DUT
(

.clk(clk),

.reset(reset),

.req(req),

.rw(rw),

.addr(addr),

.data_in(data_in),

.data_out(data_out),

.busy(busy),

.sdram_addr(sdram_addr),

.sdram_bank(sdram_bank),

.sdram_data(sdram_data),

.sdram_cs(sdram_cs),

.sdram_ras(sdram_ras),

.sdram_cas(sdram_cas),

.sdram_we(sdram_we)

);
sdram_scoreboard SCOREBOARD
(
.write_check(sb_write_check),
.read_check(sb_read_check),
.address(sb_address),
.write_data(sb_write_data),
.read_data(sb_read_data)
);


//====================================================
// SDRAM Memory Model
//====================================================

sdram_memory_model MEM_MODEL
(

.clk(clk),

.write_enable(req && rw),

.read_enable(req && !rw),

.address(addr),

.data_bus(sdram_data)

);



//====================================================
// Clock Generation
//====================================================

initial
begin

clk = 0;

forever #5 clk = ~clk;

end



//====================================================
// Functional Verification Test
//====================================================

integer i;


initial
begin


// Initial Reset

reset = 1;

req = 0;

rw = 0;

addr = 24'h000000;

data_in = 16'h0000;



#50;


reset = 0;



//====================================================
// WRITE TEST
//====================================================

for(i=0;i<5;i=i+1)

begin


#20;


req = 1;

rw = 1;


addr = i * 16;


data_in = 16'hA000 + i;



#10;


req = 0;



$display("WRITE : ADDRESS=%h DATA=%h",
addr,
data_in);



end



//====================================================
// READ TEST
//====================================================

for(i=0;i<5;i=i+1)

begin


#100;


req = 1;

rw = 0;


addr = i * 16;



#10;


req = 0;



$display("READ : ADDRESS=%h DATA=%h",
addr,
data_out);



end



#200;


$display("==============================");

$display("SDRAM FUNCTIONAL TEST COMPLETE");

$display("==============================");


$finish;


end




//====================================================
// Monitor
//====================================================

initial
begin


$monitor(

"TIME=%0t RESET=%b BUSY=%b ADDR=%h DATA=%h",

$time,

reset,

busy,

addr,

data_out

);


end




//====================================================
// Waveform Dump
//====================================================

initial
begin

$dumpfile("sdram_controller.vcd");

$dumpvars(0,tb_sdram_controller);

end



endmodule

High_Speed_SDRAM_Controller.sim/sim_1/behav/xsim/sdram_controller.vcd
$date
   Thu Sep 10 12:25:38 2026
$end
$version
  2018.2
$end
$timescale
  1ps
$end
$scope module tb_sdram_controller $end
$var reg 1 ! clk $end
$var reg 1 " reset $end
$var reg 1 # req $end
$var reg 1 $ rw $end
$var reg 24 % addr [23:0] $end
$var reg 16 & data_in [15:0] $end
$var wire 16 ' data_out [15:0] $end
$var wire 1 ( busy $end
$var wire 13 ) sdram_addr [12:0] $end
$var wire 2 * sdram_bank [1:0] $end
$var wire 16 + sdram_data [15:0] $end
$var wire 1 , sdram_cs $end
$var wire 1 - sdram_ras $end
$var wire 1 . sdram_cas $end
$var wire 1 / sdram_we $end
$var integer 32 0 i $end
$var wire 1 1 sb_write_check $end
$var wire 1 2 sb_read_check $end
$var wire 1 3 sb_address $end
$var wire 1 4 sb_write_data $end
$var wire 1 5 sb_read_data $end
$scope module DUT $end
$var wire 1 6 clk $end
$var wire 1 7 reset $end
$var wire 1 8 req $end
$var wire 1 9 rw $end
$var wire 24 : addr [23:0] $end
$var wire 16 ; data_in [15:0] $end
$var reg 16 < data_out [15:0] $end
$var wire 1 ( busy $end
$var wire 13 ) sdram_addr [12:0] $end
$var wire 2 * sdram_bank [1:0] $end
$var wire 16 + sdram_data [15:0] $end
$var wire 1 , sdram_cs $end
$var wire 1 - sdram_ras $end
$var wire 1 . sdram_cas $end
$var wire 1 / sdram_we $end
$var wire 4 = state [3:0] $end
$var wire 13 > row_address [12:0] $end
$var wire 10 ? column_address [9:0] $end
$var wire 16 @ write_data_bus [15:0] $end
$scope module FSM $end
$var wire 1 6 clk $end
$var wire 1 7 reset $end
$var reg 4 A state [3:0] $end
$var parameter 4 B IDLE [3:0] $end
$var parameter 4 C INIT [3:0] $end
$var parameter 4 D ACTIVATE [3:0] $end
$var parameter 4 E READ [3:0] $end
$var parameter 4 F WRITE [3:0] $end
$var parameter 4 G PRECHARGE [3:0] $end
$var parameter 4 H REFRESH [3:0] $end
$var parameter 4 I WAIT [3:0] $end
$upscope $end
$scope module ADDR_MAP $end
$var wire 24 : address [23:0] $end
$var wire 13 > row_address [12:0] $end
$var wire 10 ? column_address [9:0] $end
$var wire 2 * bank_address [1:0] $end
$upscope $end
$upscope $end
$scope module SCOREBOARD $end
$var wire 1 1 write_check $end
$var wire 1 2 read_check $end
$var wire 24 J address [23:0] $end
$var wire 16 K write_data [15:0] $end
$var wire 16 L read_data [15:0] $end
$var integer 32 M i $end
$upscope $end
$scope module MEM_MODEL $end
$var wire 1 N clk $end
$var wire 1 O write_enable $end
$var wire 1 P read_enable $end
$var wire 24 Q address [23:0] $end
$var wire 16 + data_bus [15:0] $end
$var reg 16 R data_out [15:0] $end
$upscope $end
$upscope $end
$enddefinitions $end
#0
$dumpvars
0!
1"
0#
0$
b0 %
b0 &
bx '
x(
b0 )
b0 *
bz +
0,
1-
1.
1/
bx 0
z1
z2
z3
z4
z5
06
17
08
09
b0 :
b0 ;
bx <
bx =
b0 >
b0 ?
bz @
bx A
b0 B
b1 C
b10 D
b11 E
b100 F
b101 G
b110 H
b111 I
bz J
bz K
bz L
b10000000000 M
0N
0O
0P
b0 Q
bx R
$end
#5000
1!
b0 '
1(
16
b0 <
b1 =
b1 A
1N
#10000
0!
06
0N
#15000
1!
16
1N
#20000
0!
06
0N
#25000
1!
16
1N
#30000
0!
06
0N
#35000
1!
16
1N
#40000
0!
06
0N
#45000
1!
16
1N
#50000
0!
0"
b0 0
06
07
0N
#55000
1!
0(
16
b0 =
b0 A
1N
#60000
0!
06
0N
#65000
1!
1(
16
b10 =
b10 A
1N
#70000
0!
1#
1$
b0 %
b1010000000000000 &
b1010000000000000 +
06
18
19
b1010000000000000 ;
0N
1O
0P
#75000
1!
b1010000000000000 '
1(
16
b1010000000000000 <
b111 =
b111 A
1N
#80000
0!
0#
bz +
b1 0
06
08
0N
0O
0P
#85000
1!
1(
16
b11 =
b11 A
1N
#90000
0!
06
0N
#95000
1!
1(
16
b101 =
b101 A
1N
#100000
0!
1#
b10000 %
b1010000000000001 &
b1010000000000001 +
06
18
b10000 :
b1010000000000001 ;
b10000 ?
0N
1O
0P
b10000 Q
#105000
1!
b1010000000000001 '
1(
16
b1010000000000001 <
b110 =
b110 A
1N
#110000
0!
0#
bz +
b10 0
06
08
0N
0O
0P
#115000
1!
0(
16
b0 =
b0 A
1N
#120000
0!
06
0N
#125000
1!
1(
16
b10 =
b10 A
1N
#130000
0!
1#
b100000 %
b1010000000000010 &
b1010000000000010 +
06
18
b100000 :
b1010000000000010 ;
b100000 ?
0N
1O
0P
b100000 Q
#135000
1!
b1010000000000010 '
1(
16
b1010000000000010 <
b111 =
b111 A
1N
#140000
0!
0#
bz +
b11 0
06
08
0N
0O
0P
#145000
1!
1(
16
b11 =
b11 A
1N
#150000
0!
06
0N
#155000
1!
1(
16
b101 =
b101 A
1N
#160000
0!
1#
b110000 %
b1010000000000011 &
b1010000000000011 +
06
18
b110000 :
b1010000000000011 ;
b110000 ?
0N
1O
0P
b110000 Q
#165000
1!
b1010000000000011 '
1(
16
b1010000000000011 <
b110 =
b110 A
1N
#170000
0!
0#
bz +
b100 0
06
08
0N
0O
0P
#175000
1!
0(
16
b0 =
b0 A
1N
#180000
0!
06
0N
#185000
1!
1(
16
b10 =
b10 A
1N
#190000
0!
1#
b1000000 %
b1010000000000100 &
b1010000000000100 +
06
18
b1000000 :
b1010000000000100 ;
b1000000 ?
0N
1O
0P
b1000000 Q
#195000
1!
b1010000000000100 '
1(
16
b1010000000000100 <
b111 =
b111 A
1N
#200000
0!
0#
bz +
b0 0
06
08
0N
0O
0P
#205000
1!
1(
16
b11 =
b11 A
1N
#210000
0!
06
0N
#215000
1!
1(
16
b101 =
b101 A
1N
#220000
0!
06
0N
#225000
1!
1(
16
b110 =
b110 A
1N
#230000
0!
06
0N
#235000
1!
0(
16
b0 =
b0 A
1N
#240000
0!
06
0N
#245000
1!
1(
16
b10 =
b10 A
1N
#250000
0!
06
0N
#255000
1!
1(
16
b111 =
b111 A
1N
#260000
0!
06
0N
#265000
1!
1(
16
b11 =
b11 A
1N
#270000
0!
06
0N
#275000
1!
1(
16
b101 =
b101 A
1N
#280000
0!
06
0N
#285000
1!
1(
16
b110 =
b110 A
1N
#290000
0!
06
0N
#295000
1!
0(
16
b0 =
b0 A
1N
#300000
0!
1#
0$
b0 %
bx +
06
18
09
b0 :
b0 ?
0N
1P
b0 Q
#305000
1!
1(
b1010000000000000 +
16
b10 =
b10 A
1N
b1010000000000000 R
#310000
0!
0#
bz +
b1 0
06
08
0N
0P
#315000
1!
1(
16
b111 =
b111 A
1N
#320000
0!
06
0N
#325000
1!
1(
16
b11 =
b11 A
1N
#330000
0!
06
0N
#335000
1!
1(
16
b101 =
b101 A
1N
#340000
0!
06
0N
#345000
1!
1(
16
b110 =
b110 A
1N
#350000
0!
06
0N
#355000
1!
0(
16
b0 =
b0 A
1N
#360000
0!
06
0N
#365000
1!
1(
16
b10 =
b10 A
1N
#370000
0!
06
0N
#375000
1!
1(
16
b111 =
b111 A
1N
#380000
0!
06
0N
#385000
1!
1(
16
b11 =
b11 A
1N
#390000
0!
06
0N
#395000
1!
1(
16
b101 =
b101 A
1N
#400000
0!
06
0N
#405000
1!
1(
16
b110 =
b110 A
1N
#410000
0!
1#
b10000 %
b1010000000000000 +
06
18
b10000 :
b10000 ?
0N
1P
b10000 Q
#415000
1!
0(
b1010000000000001 +
16
b0 =
b0 A
1N
b1010000000000001 R
#420000
0!
0#
bz +
b10 0
06
08
0N
0P
#425000
1!
1(
16
b10 =
b10 A
1N
#430000
0!
06
0N
#435000
1!
1(
16
b111 =
b111 A
1N
#440000
0!
06
0N
#445000
1!
1(
16
b11 =
b11 A
1N
#450000
0!
06
0N
#455000
1!
1(
16
b101 =
b101 A
1N
#460000
0!
06
0N
#465000
1!
1(
16
b110 =
b110 A
1N
#470000
0!
06
0N
#475000
1!
0(
16
b0 =
b0 A
1N
#480000
0!
06
0N
#485000
1!
1(
16
b10 =
b10 A
1N
#490000
0!
06
0N
#495000
1!
1(
16
b111 =
b111 A
1N
#500000
0!
06
0N
#505000
1!
1(
16
b11 =
b11 A
1N
#510000
0!
06
0N
#515000
1!
1(
16
b101 =
b101 A
1N
#520000
0!
1#
b100000 %
b1010000000000001 +
06
18
b100000 :
b100000 ?
0N
1P
b100000 Q
#525000
1!
1(
b1010000000000010 +
16
b110 =
b110 A
1N
b1010000000000010 R
#530000
0!
0#
bz +
b11 0
06
08
0N
0P
#535000
1!
0(
16
b0 =
b0 A
1N
#540000
0!
06
0N
#545000
1!
1(
16
b10 =
b10 A
1N
#550000
0!
06
0N
#555000
1!
1(
16
b111 =
b111 A
1N
#560000
0!
06
0N
#565000
1!
1(
16
b11 =
b11 A
1N
#570000
0!
06
0N
#575000
1!
1(
16
b101 =
b101 A
1N
#580000
0!
06
0N
#585000
1!
1(
16
b110 =
b110 A
1N
#590000
0!
06
0N
#595000
1!
0(
16
b0 =
b0 A
1N
#600000
0!
06
0N
#605000
1!
1(
16
b10 =
b10 A
1N
#610000
0!
06
0N
#615000
1!
1(
16
b111 =
b111 A
1N
#620000
0!
06
0N
#625000
1!
1(
16
b11 =
b11 A
1N
#630000
0!
1#
b110000 %
b1010000000000010 +
06
18
b110000 :
b110000 ?
0N
1P
b110000 Q
#635000
1!
1(
b1010000000000011 +
16
b101 =
b101 A
1N
b1010000000000011 R
#640000
0!
0#
bz +
b100 0
06
08
0N
0P
#645000
1!
1(
16
b110 =
b110 A
1N
#650000
0!
06
0N
#655000
1!
0(
16
b0 =
b0 A
1N
#660000
0!
06
0N
#665000
1!
1(
16
b10 =
b10 A
1N
#670000
0!
06
0N
#675000
1!
1(
16
b111 =
b111 A
1N
#680000
0!
06
0N
#685000
1!
1(
16
b11 =
b11 A
1N
#690000
0!
06
0N
#695000
1!
1(
16
b101 =
b101 A
1N
#700000
0!
06
0N
#705000
1!
1(
16
b110 =
b110 A
1N
#710000
0!
06
0N
#715000
1!
0(
16
b0 =
b0 A
1N
#720000
0!
06
0N
#725000
1!
1(
16
b10 =
b10 A
1N
#730000
0!
06
0N
#735000
1!
1(
16
b111 =
b111 A
1N
#740000
0!
1#
b1000000 %
b1010000000000011 +
06
18
b1000000 :
b1000000 ?
0N
1P
b1000000 Q
#745000
1!
1(
b1010000000000100 +
16
b11 =
b11 A
1N
b1010000000000100 R
#750000
0!
0#
bz +
b101 0
06
08
0N
0P
#755000
1!
1(
16
b101 =
b101 A
1N
#760000
0!
06
0N
#765000
1!
1(
16
b110 =
b110 A
1N
#770000
0!
06
0N
#775000
1!
0(
16
b0 =
b0 A
1N
#780000
0!
06
0N
#785000
1!
1(
16
b10 =
b10 A
1N
#790000
0!
06
0N
#795000
1!
1(
16
b111 =
b111 A
1N
#800000
0!
06
0N
#805000
1!
1(
16
b11 =
b11 A
1N
#810000
0!
06
0N
#815000
1!
1(
16
b101 =
b101 A
1N
#820000
0!
06
0N
#825000
1!
1(
16
b110 =
b110 A
1N
#830000
0!
06
0N
#835000
1!
0(
16
b0 =
b0 A
1N
#840000
0!
06
0N
#845000
1!
1(
16
b10 =
b10 A
1N
#850000
0!
06
0N
#855000
1!
1(
16
b111 =
b111 A
1N
#860000
0!
06
0N
#865000
1!
1(
16
b11 =
b11 A
1N
#870000
0!
06
0N
#875000
1!
1(
16
b101 =
b101 A
1N
#880000
0!
06
0N
#885000
1!
1(
16
b110 =
b110 A
1N
#890000
0!
06
0N
#895000
1!
0(
16
b0 =
b0 A
1N
#900000
0!
06
0N
#905000
1!
1(
16
b10 =
b10 A
1N
#910000
0!
06
0N
#915000
1!
1(
16
b111 =
b111 A
1N
#920000
0!
06
0N
#925000
1!
1(
16
b11 =
b11 A
1N
#930000
0!
06
0N
#935000
1!
1(
16
b101 =
b101 A
1N
